{"cameraMode":{"drawMode":0,"name":"Shaded","section":"Shading Mode"},"sceneLighting":true,"audioPlay":false,"sceneViewState":{"showFog":true,"showMaterialUpdate":false,"showSkybox":true,"showFlares":true,"showImageEffects":true,"showParticleSystems":true},"in2DMode":false,"pivot":{"x":0.37510251998901369,"y":0.635344386100769,"z":-0.2882957458496094},"rotation":{"x":-0.03229369968175888,"y":0.5194136500358582,"z":-0.019647585228085519,"w":-0.853691577911377},"size":2.1500179767608644,"orthographic":false}